tractusx_sdk/__init__.py
tractusx_sdk/dataspace/.gitignore
tractusx_sdk/dataspace/README.md
tractusx_sdk/dataspace/__init__.py
tractusx_sdk/dataspace/adapters/__init__.py
tractusx_sdk/dataspace/adapters/adapter.py
tractusx_sdk/dataspace/adapters/connector/__init__.py
tractusx_sdk/dataspace/adapters/connector/adapter_factory.py
tractusx_sdk/dataspace/adapters/connector/base_dma_adapter.py
tractusx_sdk/dataspace/adapters/connector/jupiter/__init__.py
tractusx_sdk/dataspace/adapters/connector/jupiter/dma_adapter.py
tractusx_sdk/dataspace/adapters/connector/saturn/__init__.py
tractusx_sdk/dataspace/adapters/connector/saturn/dma_adapter.py
tractusx_sdk/dataspace/constants.py
tractusx_sdk/dataspace/controllers/__init__.py
tractusx_sdk/dataspace/controllers/connector/__init__.py
tractusx_sdk/dataspace/controllers/connector/base_dma_controller.py
tractusx_sdk/dataspace/controllers/connector/controller_factory.py
tractusx_sdk/dataspace/controllers/connector/jupiter/__init__.py
tractusx_sdk/dataspace/controllers/connector/jupiter/asset_controller.py
tractusx_sdk/dataspace/controllers/connector/jupiter/catalog_controller.py
tractusx_sdk/dataspace/controllers/connector/jupiter/contract_agreement_controller.py
tractusx_sdk/dataspace/controllers/connector/jupiter/contract_definition_controller.py
tractusx_sdk/dataspace/controllers/connector/jupiter/contract_negotiation_controller.py
tractusx_sdk/dataspace/controllers/connector/jupiter/dma_controller.py
tractusx_sdk/dataspace/controllers/connector/jupiter/edr_controller.py
tractusx_sdk/dataspace/controllers/connector/jupiter/policy_controller.py
tractusx_sdk/dataspace/controllers/connector/jupiter/transfer_process_controller.py
tractusx_sdk/dataspace/controllers/connector/saturn/__init__.py
tractusx_sdk/dataspace/controllers/connector/saturn/application_observability_controller.py
tractusx_sdk/dataspace/controllers/connector/saturn/asset_controller.py
tractusx_sdk/dataspace/controllers/connector/saturn/catalog_controller.py
tractusx_sdk-0.5.0.dist-info/METADATA
tractusx_sdk-0.5.0.dist-info/WHEEL
tractusx_sdk-0.5.0.dist-info/licenses/AUTHORS.md
tractusx_sdk-0.5.0.dist-info/licenses/LICENSE
tractusx_sdk-0.5.0.dist-info/licenses/LICENSE_non-code
tractusx_sdk-0.5.0.dist-info/licenses/NOTICE.md
tractusx_sdk-0.5.0.dist-info/RECORD
