Metadata-Version: 2.4
Name: tractusx_sdk
Version: 0.5.0
Summary: Eclipse Tractus-X Software Development KIT - The Dataspace & Industry Foundation Middleware
License: Apache-2.0
License-File: AUTHORS.md
License-File: LICENSE
License-File: LICENSE_non-code
License-File: NOTICE.md
Requires-Python: >=3.12,<4.0
Classifier: License :: OSI Approved :: Apache Software License
Classifier: Programming Language :: Python :: 3
Classifier: Programming Language :: Python :: 3.12
Classifier: Programming Language :: Python :: 3.13
Classifier: Programming Language :: Python :: 3.14
Requires-Dist: annotated-types (>=0.7.0,<0.8.0)
Requires-Dist: deprecation (>=2.1.0,<3.0.0)
Requires-Dist: email-validator (>=2.2.0,<3.0.0)
Requires-Dist: exceptiongroup (>=1.2.0,<2.0.0)
Requires-Dist: fastapi (>=0.115.0,<1.0.0)
Requires-Dist: fastapi-keycloak-middleware (>=1.1.0,<2.0.0)
Requires-Dist: filelock (>=3.18.0,<4.0.0)
Requires-Dist: httpx (>=0.26.0,<0.27.0)
Requires-Dist: jinja2 (>=3.1.4,<4.0.0)
Requires-Dist: jsonschema (>=4.0.0,<5.0.0)
Requires-Dist: keycloak (>=3.1.5,<4.0.0)
Requires-Dist: pydantic (>=2.6.3,<3.0.0)
Requires-Dist: pydantic-core (>=2.16.3,<3.0.0)
Requires-Dist: python-dotenv (>=1.0.0,<2.0.0)
Requires-Dist: python-keycloak (>=4.0.1,<5.0.0)
Requires-Dist: python-multipart (>=0.0.20,<0.1.0)
Requires-Dist: pyyaml (>=6.0.0,<7.0.0)
Requires-Dist: requests (>=2.32.0,<3.0.0)
Requires-Dist: requests-toolbelt (>=1.0.0,<2.0.0)
Requires-Dist: sqlalchemy (>=2.0.38,<3.0.0)
Requires-Dist: sqlmodel (>=0.0.22,<0.1.0)
Requires-Dist: tomli (>=2.0.1,<3.0.0)
Requires-Dist: typer (>=0.15.0,<0.16.0)
Requires-Dist: uvicorn (>=0.30.0,<0.35.0)
Requires-Dist: uvloop (>=0.21.0,<0.22.0) ; sys_platform == "linux" or sys_platform == "darwin"
Requires-Dist: winloop (>=0.1.8,<0.2.0) ; sys_platform == "win32"
Project-URL: Changelog, https://github.com/eclipse-tractusx/tractusx-sdk/blob/main/CHANGELOG.md
Project-URL: Documentation, https://github.com/eclipse-tractusx/tractusx-sdk/tree/main/docs
Project-URL: Issues, https://github.com/eclipse-tractusx/tractusx-sdk/issues
Project-URL: Repository, https://github.com/eclipse-tractusx/tractusx-sdk
